thumby.py
thumby-0.2.0.dist-info/LICENSE
thumby-0.2.0.dist-info/METADATA
thumby-0.2.0.dist-info/WHEEL
thumby-0.2.0.dist-info/top_level.txt
thumby-0.2.0.dist-info/RECORD
