Metadata-Version: 2.1
Name: thumby
Version: 0.2.0
Summary: Simple python library for inserting .png thumbnails into gcode files.
Home-page: https://github.com/ThunderFly-aerospace/thumby/
Author: Dusan Jansky
License: MIT
Platform: UNKNOWN
Requires-Dist: Pillow (>=9.0.1)
Provides-Extra: dev
Requires-Dist: pytest ; extra == 'dev'
Requires-Dist: pytest-runner ; extra == 'dev'
